[
  {
    "name": "Alex",
    "slug": "alex",
    "ghin": "",
    "events": [
      {
        "event_name": "West Seattle",
        "date": "2025/06/29",
        "course": "West Seattle",
        "par": [
          5,
          4,
          3,
          5,
          4,
          3,
          4,
          4,
          5,
          4,
          3,
          5,
          3,
          4,
          4,
          4,
          4,
          4
        ],
        "holes": [
          5,
          4,
          3,
          6,
          3,
          4,
          7,
          4,
          5,
          5,
          3,
          8,
          2,
          5,
          6,
          4,
          5,
          3
        ],
        "gross": 82,
        "net": 70.52699115044247
      },
      {
        "event_name": "Maplewood",
        "date": "2025/07/12",
        "course": "Maplewood",
        "par": [
          4,
          3,
          4,
          4,
          5,
          3,
          5,
          4,
          4,
          5,
          4,
          3,
          4,
          3,
          5,
          4,
          4,
          4
        ],
        "holes": [
          0,
          0,
          0,
          0,
          0,
          0,
          0,
          0,
          0,
          0,
          0,
          0,
          0,
          0,
          0,
          0,
          0,
          0
        ],
        "gross": 0,
        "net": 0
      },
      {
        "event_name": "Willows",
        "date": "2025/07/20",
        "course": "Willows - Eagle",
        "par": [
          4,
          5,
          4,
          4,
          4,
          4,
          3,
          4,
          3,
          5,
          5,
          4,
          4,
          3,
          4,
          4,
          3,
          5
        ],
        "holes": [
          0,
          0,
          0,
          0,
          0,
          0,
          0,
          0,
          0,
          0,
          0,
          0,
          0,
          0,
          0,
          0,
          0,
          0
        ],
        "gross": 0,
        "net": 0
      },
      {
        "event_name": "Echo Falls",
        "date": "2025/08/02",
        "course": "Echo Falls",
        "par": [
          4,
          4,
          4,
          5,
          3,
          5,
          3,
          4,
          4,
          3,
          4,
          5,
          3,
          3,
          5,
          4,
          4,
          3
        ],
        "holes": [
          0,
          0,
          0,
          0,
          0,
          0,
          0,
          0,
          0,
          0,
          0,
          0,
          0,
          0,
          0,
          0,
          0,
          0
        ],
        "gross": 0,
        "net": 0
      },
      {
        "event_name": "Mt Si",
        "date": "2025/08/16",
        "course": "Mt Si",
        "par": [
          4,
          5,
          4,
          3,
          4,
          4,
          5,
          3,
          4,
          4,
          3,
          5,
          4,
          4,
          4,
          5,
          3,
          4
        ],
        "holes": [
          0,
          0,
          0,
          0,
          0,
          0,
          0,
          0,
          0,
          0,
          0,
          0,
          0,
          0,
          0,
          0,
          0,
          0
        ],
        "gross": 0,
        "net": 0
      },
      {
        "event_name": "Jackson",
        "date": "2025/09/06",
        "course": "Jackson",
        "par": [
          5,
          3,
          4,
          4,
          5,
          4,
          3,
          4,
          4,
          4,
          3,
          5,
          3,
          4,
          4,
          4,
          3,
          4
        ],
        "holes": [
          7,
          4,
          5,
          4,
          7,
          5,
          4,
          6,
          6,
          5,
          4,
          8,
          5,
          6,
          4,
          4,
          4,
          7
        ],
        "gross": 95,
        "net": 95
      }
    ],
    "season_averages": {
      "gross": null,
      "net": null,
      "finale_points": null,
      "purchase_points": null,
      "raffle_totals": null
    },
    "score_breakdown": {
      "eagle": 72,
      "birdie": 3,
      "par": 10,
      "bogey": 12,
      "double_or_worse": 11
    }
  },
  {
    "name": "Andrew",
    "slug": "andrew",
    "ghin": "",
    "events": [
      {
        "event_name": "West Seattle",
        "date": "2025/06/29",
        "course": "West Seattle",
        "par": [
          5,
          4,
          3,
          5,
          4,
          3,
          4,
          4,
          5,
          4,
          3,
          5,
          3,
          4,
          4,
          4,
          4,
          4
        ],
        "holes": [
          7,
          5,
          5,
          6,
          7,
          3,
          6,
          5,
          5,
          4,
          4,
          6,
          5,
          4,
          7,
          6,
          5,
          6
        ],
        "gross": 96,
        "net": 84.13513274336283
      },
      {
        "event_name": "Maplewood",
        "date": "2025/07/12",
        "course": "Maplewood",
        "par": [
          4,
          3,
          4,
          4,
          5,
          3,
          5,
          4,
          4,
          5,
          4,
          3,
          4,
          3,
          5,
          4,
          4,
          4
        ],
        "holes": [
          0,
          0,
          0,
          0,
          0,
          0,
          0,
          0,
          0,
          0,
          0,
          0,
          0,
          0,
          0,
          0,
          0,
          0
        ],
        "gross": 0,
        "net": 0
      },
      {
        "event_name": "Willows",
        "date": "2025/07/20",
        "course": "Willows - Eagle",
        "par": [
          4,
          5,
          4,
          4,
          4,
          4,
          3,
          4,
          3,
          5,
          5,
          4,
          4,
          3,
          4,
          4,
          3,
          5
        ],
        "holes": [
          0,
          0,
          0,
          0,
          0,
          0,
          0,
          0,
          0,
          0,
          0,
          0,
          0,
          0,
          0,
          0,
          0,
          0
        ],
        "gross": 0,
        "net": 0
      },
      {
        "event_name": "Echo Falls",
        "date": "2025/08/02",
        "course": "Echo Falls",
        "par": [
          4,
          4,
          4,
          5,
          3,
          5,
          3,
          4,
          4,
          3,
          4,
          5,
          3,
          3,
          5,
          4,
          4,
          3
        ],
        "holes": [
          0,
          0,
          0,
          0,
          0,
          0,
          0,
          0,
          0,
          0,
          0,
          0,
          0,
          0,
          0,
          0,
          0,
          0
        ],
        "gross": 0,
        "net": 0
      },
      {
        "event_name": "Mt Si",
        "date": "2025/08/16",
        "course": "Mt Si",
        "par": [
          4,
          5,
          4,
          3,
          4,
          4,
          5,
          3,
          4,
          4,
          3,
          5,
          4,
          4,
          4,
          5,
          3,
          4
        ],
        "holes": [
          0,
          0,
          0,
          0,
          0,
          0,
          0,
          0,
          0,
          0,
          0,
          0,
          0,
          0,
          0,
          0,
          0,
          0
        ],
        "gross": 0,
        "net": 0
      },
      {
        "event_name": "Jackson",
        "date": "2025/09/06",
        "course": "Jackson",
        "par": [
          5,
          3,
          4,
          4,
          5,
          4,
          3,
          4,
          4,
          4,
          3,
          5,
          3,
          4,
          4,
          4,
          3,
          4
        ],
        "holes": [
          6,
          6,
          4,
          5,
          4,
          6,
          4,
          6,
          5,
          4,
          3,
          7,
          4,
          6,
          5,
          6,
          5,
          4
        ],
        "gross": 90,
        "net": 90
      }
    ],
    "season_averages": {
      "gross": null,
      "net": null,
      "finale_points": null,
      "purchase_points": null,
      "raffle_totals": null
    },
    "score_breakdown": {
      "eagle": 72,
      "birdie": 1,
      "par": 8,
      "bogey": 12,
      "double_or_worse": 15
    }
  },
  {
    "name": "Brian",
    "slug": "brian",
    "ghin": "",
    "events": [
      {
        "event_name": "West Seattle",
        "date": "2025/06/29",
        "course": "West Seattle",
        "par": [
          5,
          4,
          3,
          5,
          4,
          3,
          4,
          4,
          5,
          4,
          3,
          5,
          3,
          4,
          4,
          4,
          4,
          4
        ],
        "holes": [
          7,
          6,
          5,
          9,
          7,
          4,
          5,
          6,
          7,
          6,
          5,
          6,
          4,
          6,
          5,
          6,
          6,
          6
        ],
        "gross": 106,
        "net": 87.27761061946902
      },
      {
        "event_name": "Maplewood",
        "date": "2025/07/12",
        "course": "Maplewood",
        "par": [
          4,
          3,
          4,
          4,
          5,
          3,
          5,
          4,
          4,
          5,
          4,
          3,
          4,
          3,
          5,
          4,
          4,
          4
        ],
        "holes": [
          0,
          0,
          0,
          0,
          0,
          0,
          0,
          0,
          0,
          0,
          0,
          0,
          0,
          0,
          0,
          0,
          0,
          0
        ],
        "gross": 0,
        "net": 0
      },
      {
        "event_name": "Willows",
        "date": "2025/07/20",
        "course": "Willows - Eagle",
        "par": [
          4,
          5,
          4,
          4,
          4,
          4,
          3,
          4,
          3,
          5,
          5,
          4,
          4,
          3,
          4,
          4,
          3,
          5
        ],
        "holes": [
          0,
          0,
          0,
          0,
          0,
          0,
          0,
          0,
          0,
          0,
          0,
          0,
          0,
          0,
          0,
          0,
          0,
          0
        ],
        "gross": 0,
        "net": 0
      },
      {
        "event_name": "Echo Falls",
        "date": "2025/08/02",
        "course": "Echo Falls",
        "par": [
          4,
          4,
          4,
          5,
          3,
          5,
          3,
          4,
          4,
          3,
          4,
          5,
          3,
          3,
          5,
          4,
          4,
          3
        ],
        "holes": [
          0,
          0,
          0,
          0,
          0,
          0,
          0,
          0,
          0,
          0,
          0,
          0,
          0,
          0,
          0,
          0,
          0,
          0
        ],
        "gross": 0,
        "net": 0
      },
      {
        "event_name": "Mt Si",
        "date": "2025/08/16",
        "course": "Mt Si",
        "par": [
          4,
          5,
          4,
          3,
          4,
          4,
          5,
          3,
          4,
          4,
          3,
          5,
          4,
          4,
          4,
          5,
          3,
          4
        ],
        "holes": [
          0,
          0,
          0,
          0,
          0,
          0,
          0,
          0,
          0,
          0,
          0,
          0,
          0,
          0,
          0,
          0,
          0,
          0
        ],
        "gross": 0,
        "net": 0
      },
      {
        "event_name": "Jackson",
        "date": "2025/09/06",
        "course": "Jackson",
        "par": [
          5,
          3,
          4,
          4,
          5,
          4,
          3,
          4,
          4,
          4,
          3,
          5,
          3,
          4,
          4,
          4,
          3,
          4
        ],
        "holes": [
          8,
          4,
          6,
          7,
          7,
          7,
          4,
          6,
          6,
          5,
          5,
          7,
          6,
          6,
          5,
          5,
          4,
          6
        ],
        "gross": 104,
        "net": 104
      }
    ],
    "season_averages": {
      "gross": null,
      "net": null,
      "finale_points": null,
      "purchase_points": null,
      "raffle_totals": null
    },
    "score_breakdown": {
      "eagle": 72,
      "birdie": 0,
      "par": 0,
      "bogey": 11,
      "double_or_worse": 25
    }
  },
  {
    "name": "David",
    "slug": "david",
    "ghin": "",
    "events": [
      {
        "event_name": "West Seattle",
        "date": "2025/06/29",
        "course": "West Seattle",
        "par": [
          5,
          4,
          3,
          5,
          4,
          3,
          4,
          4,
          5,
          4,
          3,
          5,
          3,
          4,
          4,
          4,
          4,
          4
        ],
        "holes": [
          10,
          4,
          6,
          7,
          7,
          4,
          5,
          5,
          5,
          5,
          5,
          10,
          4,
          5,
          7,
          8,
          8,
          6
        ],
        "gross": 111,
        "net": 96.19619469026549
      },
      {
        "event_name": "Maplewood",
        "date": "2025/07/12",
        "course": "Maplewood",
        "par": [
          4,
          3,
          4,
          4,
          5,
          3,
          5,
          4,
          4,
          5,
          4,
          3,
          4,
          3,
          5,
          4,
          4,
          4
        ],
        "holes": [
          0,
          0,
          0,
          0,
          0,
          0,
          0,
          0,
          0,
          0,
          0,
          0,
          0,
          0,
          0,
          0,
          0,
          0
        ],
        "gross": 0,
        "net": 0
      },
      {
        "event_name": "Willows",
        "date": "2025/07/20",
        "course": "Willows - Eagle",
        "par": [
          4,
          5,
          4,
          4,
          4,
          4,
          3,
          4,
          3,
          5,
          5,
          4,
          4,
          3,
          4,
          4,
          3,
          5
        ],
        "holes": [
          0,
          0,
          0,
          0,
          0,
          0,
          0,
          0,
          0,
          0,
          0,
          0,
          0,
          0,
          0,
          0,
          0,
          0
        ],
        "gross": 0,
        "net": 0
      },
      {
        "event_name": "Echo Falls",
        "date": "2025/08/02",
        "course": "Echo Falls",
        "par": [
          4,
          4,
          4,
          5,
          3,
          5,
          3,
          4,
          4,
          3,
          4,
          5,
          3,
          3,
          5,
          4,
          4,
          3
        ],
        "holes": [
          0,
          0,
          0,
          0,
          0,
          0,
          0,
          0,
          0,
          0,
          0,
          0,
          0,
          0,
          0,
          0,
          0,
          0
        ],
        "gross": 0,
        "net": 0
      },
      {
        "event_name": "Mt Si",
        "date": "2025/08/16",
        "course": "Mt Si",
        "par": [
          4,
          5,
          4,
          3,
          4,
          4,
          5,
          3,
          4,
          4,
          3,
          5,
          4,
          4,
          4,
          5,
          3,
          4
        ],
        "holes": [
          0,
          0,
          0,
          0,
          0,
          0,
          0,
          0,
          0,
          0,
          0,
          0,
          0,
          0,
          0,
          0,
          0,
          0
        ],
        "gross": 0,
        "net": 0
      },
      {
        "event_name": "Jackson",
        "date": "2025/09/06",
        "course": "Jackson",
        "par": [
          5,
          3,
          4,
          4,
          5,
          4,
          3,
          4,
          4,
          4,
          3,
          5,
          3,
          4,
          4,
          4,
          3,
          4
        ],
        "holes": [
          6,
          5,
          4,
          5,
          7,
          6,
          5,
          5,
          6,
          6,
          4,
          6,
          5,
          7,
          5,
          6,
          3,
          6
        ],
        "gross": 97,
        "net": 97
      }
    ],
    "season_averages": {
      "gross": null,
      "net": null,
      "finale_points": null,
      "purchase_points": null,
      "raffle_totals": null
    },
    "score_breakdown": {
      "eagle": 72,
      "birdie": 0,
      "par": 4,
      "bogey": 12,
      "double_or_worse": 20
    }
  },
  {
    "name": "Dean",
    "slug": "dean",
    "ghin": "",
    "events": [
      {
        "event_name": "West Seattle",
        "date": "2025/06/29",
        "course": "West Seattle",
        "par": [
          5,
          4,
          3,
          5,
          4,
          3,
          4,
          4,
          5,
          4,
          3,
          5,
          3,
          4,
          4,
          4,
          4,
          4
        ],
        "holes": [
          6,
          4,
          4,
          5,
          4,
          5,
          5,
          5,
          9,
          4,
          4,
          7,
          3,
          4,
          4,
          5,
          5,
          4
        ],
        "gross": 87,
        "net": 75.52699115044247
      },
      {
        "event_name": "Maplewood",
        "date": "2025/07/12",
        "course": "Maplewood",
        "par": [
          4,
          3,
          4,
          4,
          5,
          3,
          5,
          4,
          4,
          5,
          4,
          3,
          4,
          3,
          5,
          4,
          4,
          4
        ],
        "holes": [
          0,
          0,
          0,
          0,
          0,
          0,
          0,
          0,
          0,
          0,
          0,
          0,
          0,
          0,
          0,
          0,
          0,
          0
        ],
        "gross": 0,
        "net": 0
      },
      {
        "event_name": "Willows",
        "date": "2025/07/20",
        "course": "Willows - Eagle",
        "par": [
          4,
          5,
          4,
          4,
          4,
          4,
          3,
          4,
          3,
          5,
          5,
          4,
          4,
          3,
          4,
          4,
          3,
          5
        ],
        "holes": [
          0,
          0,
          0,
          0,
          0,
          0,
          0,
          0,
          0,
          0,
          0,
          0,
          0,
          0,
          0,
          0,
          0,
          0
        ],
        "gross": 0,
        "net": 0
      },
      {
        "event_name": "Echo Falls",
        "date": "2025/08/02",
        "course": "Echo Falls",
        "par": [
          4,
          4,
          4,
          5,
          3,
          5,
          3,
          4,
          4,
          3,
          4,
          5,
          3,
          3,
          5,
          4,
          4,
          3
        ],
        "holes": [
          0,
          0,
          0,
          0,
          0,
          0,
          0,
          0,
          0,
          0,
          0,
          0,
          0,
          0,
          0,
          0,
          0,
          0
        ],
        "gross": 0,
        "net": 0
      },
      {
        "event_name": "Mt Si",
        "date": "2025/08/16",
        "course": "Mt Si",
        "par": [
          4,
          5,
          4,
          3,
          4,
          4,
          5,
          3,
          4,
          4,
          3,
          5,
          4,
          4,
          4,
          5,
          3,
          4
        ],
        "holes": [
          0,
          0,
          0,
          0,
          0,
          0,
          0,
          0,
          0,
          0,
          0,
          0,
          0,
          0,
          0,
          0,
          0,
          0
        ],
        "gross": 0,
        "net": 0
      },
      {
        "event_name": "Jackson",
        "date": "2025/09/06",
        "course": "Jackson",
        "par": [
          5,
          3,
          4,
          4,
          5,
          4,
          3,
          4,
          4,
          4,
          3,
          5,
          3,
          4,
          4,
          4,
          3,
          4
        ],
        "holes": [
          7,
          5,
          5,
          8,
          9,
          8,
          4,
          4,
          5,
          5,
          4,
          8,
          5,
          4,
          5,
          8,
          3,
          8
        ],
        "gross": 105,
        "net": 105
      }
    ],
    "season_averages": {
      "gross": null,
      "net": null,
      "finale_points": null,
      "purchase_points": null,
      "raffle_totals": null
    },
    "score_breakdown": {
      "eagle": 72,
      "birdie": 0,
      "par": 11,
      "bogey": 13,
      "double_or_worse": 12
    }
  },
  {
    "name": "Eli",
    "slug": "eli",
    "ghin": "",
    "events": [
      {
        "event_name": "West Seattle",
        "date": "2025/06/29",
        "course": "West Seattle",
        "par": [
          5,
          4,
          3,
          5,
          4,
          3,
          4,
          4,
          5,
          4,
          3,
          5,
          3,
          4,
          4,
          4,
          4,
          4
        ],
        "holes": [
          5,
          4,
          4,
          6,
          4,
          3,
          4,
          7,
          5,
          5,
          3,
          7,
          4,
          4,
          4,
          5,
          6,
          4
        ],
        "gross": 84,
        "net": 75.85778761061947
      },
      {
        "event_name": "Maplewood",
        "date": "2025/07/12",
        "course": "Maplewood",
        "par": [
          4,
          3,
          4,
          4,
          5,
          3,
          5,
          4,
          4,
          5,
          4,
          3,
          4,
          3,
          5,
          4,
          4,
          4
        ],
        "holes": [
          0,
          0,
          0,
          0,
          0,
          0,
          0,
          0,
          0,
          0,
          0,
          0,
          0,
          0,
          0,
          0,
          0,
          0
        ],
        "gross": 0,
        "net": 0
      },
      {
        "event_name": "Willows",
        "date": "2025/07/20",
        "course": "Willows - Eagle",
        "par": [
          4,
          5,
          4,
          4,
          4,
          4,
          3,
          4,
          3,
          5,
          5,
          4,
          4,
          3,
          4,
          4,
          3,
          5
        ],
        "holes": [
          0,
          0,
          0,
          0,
          0,
          0,
          0,
          0,
          0,
          0,
          0,
          0,
          0,
          0,
          0,
          0,
          0,
          0
        ],
        "gross": 0,
        "net": 0
      },
      {
        "event_name": "Echo Falls",
        "date": "2025/08/02",
        "course": "Echo Falls",
        "par": [
          4,
          4,
          4,
          5,
          3,
          5,
          3,
          4,
          4,
          3,
          4,
          5,
          3,
          3,
          5,
          4,
          4,
          3
        ],
        "holes": [
          0,
          0,
          0,
          0,
          0,
          0,
          0,
          0,
          0,
          0,
          0,
          0,
          0,
          0,
          0,
          0,
          0,
          0
        ],
        "gross": 0,
        "net": 0
      },
      {
        "event_name": "Mt Si",
        "date": "2025/08/16",
        "course": "Mt Si",
        "par": [
          4,
          5,
          4,
          3,
          4,
          4,
          5,
          3,
          4,
          4,
          3,
          5,
          4,
          4,
          4,
          5,
          3,
          4
        ],
        "holes": [
          0,
          0,
          0,
          0,
          0,
          0,
          0,
          0,
          0,
          0,
          0,
          0,
          0,
          0,
          0,
          0,
          0,
          0
        ],
        "gross": 0,
        "net": 0
      },
      {
        "event_name": "Jackson",
        "date": "2025/09/06",
        "course": "Jackson",
        "par": [
          5,
          3,
          4,
          4,
          5,
          4,
          3,
          4,
          4,
          4,
          3,
          5,
          3,
          4,
          4,
          4,
          3,
          4
        ],
        "holes": [
          6,
          2,
          8,
          5,
          6,
          6,
          3,
          4,
          5,
          4,
          3,
          6,
          4,
          5,
          5,
          3,
          4,
          6
        ],
        "gross": 85,
        "net": 85
      }
    ],
    "season_averages": {
      "gross": null,
      "net": null,
      "finale_points": null,
      "purchase_points": null,
      "raffle_totals": null
    },
    "score_breakdown": {
      "eagle": 72,
      "birdie": 2,
      "par": 14,
      "bogey": 14,
      "double_or_worse": 6
    }
  },
  {
    "name": "Isaac",
    "slug": "isaac",
    "ghin": "",
    "events": [
      {
        "event_name": "West Seattle",
        "date": "2025/06/29",
        "course": "West Seattle",
        "par": [
          5,
          4,
          3,
          5,
          4,
          3,
          4,
          4,
          5,
          4,
          3,
          5,
          3,
          4,
          4,
          4,
          4,
          4
        ],
        "holes": [
          8,
          5,
          4,
          6,
          5,
          4,
          4,
          8,
          8,
          6,
          4,
          7,
          5,
          7,
          5,
          6,
          6,
          6
        ],
        "gross": 104,
        "net": 86.55115044247788
      },
      {
        "event_name": "Maplewood",
        "date": "2025/07/12",
        "course": "Maplewood",
        "par": [
          4,
          3,
          4,
          4,
          5,
          3,
          5,
          4,
          4,
          5,
          4,
          3,
          4,
          3,
          5,
          4,
          4,
          4
        ],
        "holes": [
          0,
          0,
          0,
          0,
          0,
          0,
          0,
          0,
          0,
          0,
          0,
          0,
          0,
          0,
          0,
          0,
          0,
          0
        ],
        "gross": 0,
        "net": 0
      },
      {
        "event_name": "Willows",
        "date": "2025/07/20",
        "course": "Willows - Eagle",
        "par": [
          4,
          5,
          4,
          4,
          4,
          4,
          3,
          4,
          3,
          5,
          5,
          4,
          4,
          3,
          4,
          4,
          3,
          5
        ],
        "holes": [
          0,
          0,
          0,
          0,
          0,
          0,
          0,
          0,
          0,
          0,
          0,
          0,
          0,
          0,
          0,
          0,
          0,
          0
        ],
        "gross": 0,
        "net": 0
      },
      {
        "event_name": "Echo Falls",
        "date": "2025/08/02",
        "course": "Echo Falls",
        "par": [
          4,
          4,
          4,
          5,
          3,
          5,
          3,
          4,
          4,
          3,
          4,
          5,
          3,
          3,
          5,
          4,
          4,
          3
        ],
        "holes": [
          0,
          0,
          0,
          0,
          0,
          0,
          0,
          0,
          0,
          0,
          0,
          0,
          0,
          0,
          0,
          0,
          0,
          0
        ],
        "gross": 0,
        "net": 0
      },
      {
        "event_name": "Mt Si",
        "date": "2025/08/16",
        "course": "Mt Si",
        "par": [
          4,
          5,
          4,
          3,
          4,
          4,
          5,
          3,
          4,
          4,
          3,
          5,
          4,
          4,
          4,
          5,
          3,
          4
        ],
        "holes": [
          0,
          0,
          0,
          0,
          0,
          0,
          0,
          0,
          0,
          0,
          0,
          0,
          0,
          0,
          0,
          0,
          0,
          0
        ],
        "gross": 0,
        "net": 0
      },
      {
        "event_name": "Jackson",
        "date": "2025/09/06",
        "course": "Jackson",
        "par": [
          5,
          3,
          4,
          4,
          5,
          4,
          3,
          4,
          4,
          4,
          3,
          5,
          3,
          4,
          4,
          4,
          3,
          4
        ],
        "holes": [
          10,
          4,
          5,
          4,
          4,
          6,
          4,
          6,
          7,
          4,
          4,
          8,
          6,
          5,
          7,
          5,
          4,
          6
        ],
        "gross": 99,
        "net": 99
      }
    ],
    "season_averages": {
      "gross": null,
      "net": null,
      "finale_points": null,
      "purchase_points": null,
      "raffle_totals": null
    },
    "score_breakdown": {
      "eagle": 72,
      "birdie": 1,
      "par": 3,
      "bogey": 14,
      "double_or_worse": 18
    }
  },
  {
    "name": "James",
    "slug": "james",
    "ghin": "",
    "events": [
      {
        "event_name": "West Seattle",
        "date": "2025/06/29",
        "course": "West Seattle",
        "par": [
          5,
          4,
          3,
          5,
          4,
          3,
          4,
          4,
          5,
          4,
          3,
          5,
          3,
          4,
          4,
          4,
          4,
          4
        ],
        "holes": [
          7,
          5,
          6,
          5,
          5,
          4,
          6,
          6,
          5,
          6,
          4,
          7,
          4,
          5,
          7,
          6,
          6,
          5
        ],
        "gross": 99,
        "net": 86.44938053097344
      },
      {
        "event_name": "Maplewood",
        "date": "2025/07/12",
        "course": "Maplewood",
        "par": [
          4,
          3,
          4,
          4,
          5,
          3,
          5,
          4,
          4,
          5,
          4,
          3,
          4,
          3,
          5,
          4,
          4,
          4
        ],
        "holes": [
          0,
          0,
          0,
          0,
          0,
          0,
          0,
          0,
          0,
          0,
          0,
          0,
          0,
          0,
          0,
          0,
          0,
          0
        ],
        "gross": 0,
        "net": 0
      },
      {
        "event_name": "Willows",
        "date": "2025/07/20",
        "course": "Willows - Eagle",
        "par": [
          4,
          5,
          4,
          4,
          4,
          4,
          3,
          4,
          3,
          5,
          5,
          4,
          4,
          3,
          4,
          4,
          3,
          5
        ],
        "holes": [
          0,
          0,
          0,
          0,
          0,
          0,
          0,
          0,
          0,
          0,
          0,
          0,
          0,
          0,
          0,
          0,
          0,
          0
        ],
        "gross": 0,
        "net": 0
      },
      {
        "event_name": "Echo Falls",
        "date": "2025/08/02",
        "course": "Echo Falls",
        "par": [
          4,
          4,
          4,
          5,
          3,
          5,
          3,
          4,
          4,
          3,
          4,
          5,
          3,
          3,
          5,
          4,
          4,
          3
        ],
        "holes": [
          0,
          0,
          0,
          0,
          0,
          0,
          0,
          0,
          0,
          0,
          0,
          0,
          0,
          0,
          0,
          0,
          0,
          0
        ],
        "gross": 0,
        "net": 0
      },
      {
        "event_name": "Mt Si",
        "date": "2025/08/16",
        "course": "Mt Si",
        "par": [
          4,
          5,
          4,
          3,
          4,
          4,
          5,
          3,
          4,
          4,
          3,
          5,
          4,
          4,
          4,
          5,
          3,
          4
        ],
        "holes": [
          0,
          0,
          0,
          0,
          0,
          0,
          0,
          0,
          0,
          0,
          0,
          0,
          0,
          0,
          0,
          0,
          0,
          0
        ],
        "gross": 0,
        "net": 0
      }
    ],
    "season_averages": {
      "gross": null,
      "net": null,
      "finale_points": null,
      "purchase_points": null,
      "raffle_totals": null
    },
    "score_breakdown": {
      "eagle": 72,
      "birdie": 0,
      "par": 2,
      "bogey": 7,
      "double_or_worse": 9
    }
  },
  {
    "name": "Johnny",
    "slug": "johnny",
    "ghin": "",
    "events": [
      {
        "event_name": "West Seattle",
        "date": "2025/06/29",
        "course": "West Seattle",
        "par": [
          5,
          4,
          3,
          5,
          4,
          3,
          4,
          4,
          5,
          4,
          3,
          5,
          3,
          4,
          4,
          4,
          4,
          4
        ],
        "holes": [
          7,
          6,
          4,
          5,
          7,
          6,
          4,
          8,
          6,
          5,
          4,
          10,
          4,
          6,
          7,
          6,
          6,
          5
        ],
        "gross": 106,
        "net": 91.97991150442478
      },
      {
        "event_name": "Maplewood",
        "date": "2025/07/12",
        "course": "Maplewood",
        "par": [
          4,
          3,
          4,
          4,
          5,
          3,
          5,
          4,
          4,
          5,
          4,
          3,
          4,
          3,
          5,
          4,
          4,
          4
        ],
        "holes": [
          0,
          0,
          0,
          0,
          0,
          0,
          0,
          0,
          0,
          0,
          0,
          0,
          0,
          0,
          0,
          0,
          0,
          0
        ],
        "gross": 0,
        "net": 0
      },
      {
        "event_name": "Willows",
        "date": "2025/07/20",
        "course": "Willows - Eagle",
        "par": [
          4,
          5,
          4,
          4,
          4,
          4,
          3,
          4,
          3,
          5,
          5,
          4,
          4,
          3,
          4,
          4,
          3,
          5
        ],
        "holes": [
          0,
          0,
          0,
          0,
          0,
          0,
          0,
          0,
          0,
          0,
          0,
          0,
          0,
          0,
          0,
          0,
          0,
          0
        ],
        "gross": 0,
        "net": 0
      },
      {
        "event_name": "Echo Falls",
        "date": "2025/08/02",
        "course": "Echo Falls",
        "par": [
          4,
          4,
          4,
          5,
          3,
          5,
          3,
          4,
          4,
          3,
          4,
          5,
          3,
          3,
          5,
          4,
          4,
          3
        ],
        "holes": [
          0,
          0,
          0,
          0,
          0,
          0,
          0,
          0,
          0,
          0,
          0,
          0,
          0,
          0,
          0,
          0,
          0,
          0
        ],
        "gross": 0,
        "net": 0
      },
      {
        "event_name": "Mt Si",
        "date": "2025/08/16",
        "course": "Mt Si",
        "par": [
          4,
          5,
          4,
          3,
          4,
          4,
          5,
          3,
          4,
          4,
          3,
          5,
          4,
          4,
          4,
          5,
          3,
          4
        ],
        "holes": [
          0,
          0,
          0,
          0,
          0,
          0,
          0,
          0,
          0,
          0,
          0,
          0,
          0,
          0,
          0,
          0,
          0,
          0
        ],
        "gross": 0,
        "net": 0
      },
      {
        "event_name": "Jackson",
        "date": "2025/09/06",
        "course": "Jackson",
        "par": [
          5,
          3,
          4,
          4,
          5,
          4,
          3,
          4,
          4,
          4,
          3,
          5,
          3,
          4,
          4,
          4,
          3,
          4
        ],
        "holes": [
          7,
          5,
          6,
          6,
          8,
          7,
          4,
          5,
          6,
          8,
          3,
          6,
          5,
          7,
          7,
          8,
          6,
          5
        ],
        "gross": 109,
        "net": 109
      }
    ],
    "season_averages": {
      "gross": null,
      "net": null,
      "finale_points": null,
      "purchase_points": null,
      "raffle_totals": null
    },
    "score_breakdown": {
      "eagle": 72,
      "birdie": 0,
      "par": 3,
      "bogey": 10,
      "double_or_worse": 23
    }
  },
  {
    "name": "Michael",
    "slug": "michael",
    "ghin": "",
    "events": [
      {
        "event_name": "West Seattle",
        "date": "2025/06/29",
        "course": "West Seattle",
        "par": [
          5,
          4,
          3,
          5,
          4,
          3,
          4,
          4,
          5,
          4,
          3,
          5,
          3,
          4,
          4,
          4,
          4,
          4
        ],
        "holes": [
          7,
          6,
          5,
          7,
          4,
          4,
          4,
          5,
          8,
          4,
          3,
          7,
          4,
          4,
          4,
          5,
          7,
          6
        ],
        "gross": 94,
        "net": 76.15929203539822
      },
      {
        "event_name": "Maplewood",
        "date": "2025/07/12",
        "course": "Maplewood",
        "par": [
          4,
          3,
          4,
          4,
          5,
          3,
          5,
          4,
          4,
          5,
          4,
          3,
          4,
          3,
          5,
          4,
          4,
          4
        ],
        "holes": [
          0,
          0,
          0,
          0,
          0,
          0,
          0,
          0,
          0,
          0,
          0,
          0,
          0,
          0,
          0,
          0,
          0,
          0
        ],
        "gross": 0,
        "net": 0
      },
      {
        "event_name": "Willows",
        "date": "2025/07/20",
        "course": "Willows - Eagle",
        "par": [
          4,
          5,
          4,
          4,
          4,
          4,
          3,
          4,
          3,
          5,
          5,
          4,
          4,
          3,
          4,
          4,
          3,
          5
        ],
        "holes": [
          0,
          0,
          0,
          0,
          0,
          0,
          0,
          0,
          0,
          0,
          0,
          0,
          0,
          0,
          0,
          0,
          0,
          0
        ],
        "gross": 0,
        "net": 0
      },
      {
        "event_name": "Echo Falls",
        "date": "2025/08/02",
        "course": "Echo Falls",
        "par": [
          4,
          4,
          4,
          5,
          3,
          5,
          3,
          4,
          4,
          3,
          4,
          5,
          3,
          3,
          5,
          4,
          4,
          3
        ],
        "holes": [
          0,
          0,
          0,
          0,
          0,
          0,
          0,
          0,
          0,
          0,
          0,
          0,
          0,
          0,
          0,
          0,
          0,
          0
        ],
        "gross": 0,
        "net": 0
      },
      {
        "event_name": "Mt Si",
        "date": "2025/08/16",
        "course": "Mt Si",
        "par": [
          4,
          5,
          4,
          3,
          4,
          4,
          5,
          3,
          4,
          4,
          3,
          5,
          4,
          4,
          4,
          5,
          3,
          4
        ],
        "holes": [
          0,
          0,
          0,
          0,
          0,
          0,
          0,
          0,
          0,
          0,
          0,
          0,
          0,
          0,
          0,
          0,
          0,
          0
        ],
        "gross": 0,
        "net": 0
      },
      {
        "event_name": "Jackson",
        "date": "2025/09/06",
        "course": "Jackson",
        "par": [
          5,
          3,
          4,
          4,
          5,
          4,
          3,
          4,
          4,
          4,
          3,
          5,
          3,
          4,
          4,
          4,
          3,
          4
        ],
        "holes": [
          9,
          3,
          4,
          7,
          6,
          5,
          4,
          6,
          5,
          5,
          4,
          7,
          4,
          6,
          5,
          5,
          5,
          5
        ],
        "gross": 95,
        "net": 95
      }
    ],
    "season_averages": {
      "gross": null,
      "net": null,
      "finale_points": null,
      "purchase_points": null,
      "raffle_totals": null
    },
    "score_breakdown": {
      "eagle": 72,
      "birdie": 0,
      "par": 8,
      "bogey": 14,
      "double_or_worse": 14
    }
  },
  {
    "name": "Philip",
    "slug": "philip",
    "ghin": "",
    "events": [
      {
        "event_name": "West Seattle",
        "date": "2025/06/29",
        "course": "West Seattle",
        "par": [
          5,
          4,
          3,
          5,
          4,
          3,
          4,
          4,
          5,
          4,
          3,
          5,
          3,
          4,
          4,
          4,
          4,
          4
        ],
        "holes": [
          5,
          4,
          3,
          7,
          3,
          4,
          4,
          5,
          5,
          4,
          4,
          3,
          4,
          4,
          6,
          5,
          4,
          4
        ],
        "gross": 78,
        "net": 65.74327433628318
      },
      {
        "event_name": "Maplewood",
        "date": "2025/07/12",
        "course": "Maplewood",
        "par": [
          4,
          3,
          4,
          4,
          5,
          3,
          5,
          4,
          4,
          5,
          4,
          3,
          4,
          3,
          5,
          4,
          4,
          4
        ],
        "holes": [
          0,
          0,
          0,
          0,
          0,
          0,
          0,
          0,
          0,
          0,
          0,
          0,
          0,
          0,
          0,
          0,
          0,
          0
        ],
        "gross": 0,
        "net": 0
      },
      {
        "event_name": "Willows",
        "date": "2025/07/20",
        "course": "Willows - Eagle",
        "par": [
          4,
          5,
          4,
          4,
          4,
          4,
          3,
          4,
          3,
          5,
          5,
          4,
          4,
          3,
          4,
          4,
          3,
          5
        ],
        "holes": [
          0,
          0,
          0,
          0,
          0,
          0,
          0,
          0,
          0,
          0,
          0,
          0,
          0,
          0,
          0,
          0,
          0,
          0
        ],
        "gross": 0,
        "net": 0
      },
      {
        "event_name": "Echo Falls",
        "date": "2025/08/02",
        "course": "Echo Falls",
        "par": [
          4,
          4,
          4,
          5,
          3,
          5,
          3,
          4,
          4,
          3,
          4,
          5,
          3,
          3,
          5,
          4,
          4,
          3
        ],
        "holes": [
          0,
          0,
          0,
          0,
          0,
          0,
          0,
          0,
          0,
          0,
          0,
          0,
          0,
          0,
          0,
          0,
          0,
          0
        ],
        "gross": 0,
        "net": 0
      },
      {
        "event_name": "Mt Si",
        "date": "2025/08/16",
        "course": "Mt Si",
        "par": [
          4,
          5,
          4,
          3,
          4,
          4,
          5,
          3,
          4,
          4,
          3,
          5,
          4,
          4,
          4,
          5,
          3,
          4
        ],
        "holes": [
          0,
          0,
          0,
          0,
          0,
          0,
          0,
          0,
          0,
          0,
          0,
          0,
          0,
          0,
          0,
          0,
          0,
          0
        ],
        "gross": 0,
        "net": 0
      }
    ],
    "season_averages": {
      "gross": null,
      "net": null,
      "finale_points": null,
      "purchase_points": null,
      "raffle_totals": null
    },
    "score_breakdown": {
      "eagle": 73,
      "birdie": 1,
      "par": 9,
      "bogey": 5,
      "double_or_worse": 2
    }
  },
  {
    "name": "Richie",
    "slug": "richie",
    "ghin": "",
    "events": [
      {
        "event_name": "West Seattle",
        "date": "2025/06/29",
        "course": "West Seattle",
        "par": [
          5,
          4,
          3,
          5,
          4,
          3,
          4,
          4,
          5,
          4,
          3,
          5,
          3,
          4,
          4,
          4,
          4,
          4
        ],
        "holes": [
          8,
          5,
          3,
          5,
          5,
          4,
          4,
          8,
          5,
          5,
          4,
          4,
          2,
          5,
          4,
          5,
          6,
          4
        ],
        "gross": 86,
        "net": 76.68221238938052
      },
      {
        "event_name": "Maplewood",
        "date": "2025/07/12",
        "course": "Maplewood",
        "par": [
          4,
          3,
          4,
          4,
          5,
          3,
          5,
          4,
          4,
          5,
          4,
          3,
          4,
          3,
          5,
          4,
          4,
          4
        ],
        "holes": [
          0,
          0,
          0,
          0,
          0,
          0,
          0,
          0,
          0,
          0,
          0,
          0,
          0,
          0,
          0,
          0,
          0,
          0
        ],
        "gross": 0,
        "net": 0
      },
      {
        "event_name": "Willows",
        "date": "2025/07/20",
        "course": "Willows - Eagle",
        "par": [
          4,
          5,
          4,
          4,
          4,
          4,
          3,
          4,
          3,
          5,
          5,
          4,
          4,
          3,
          4,
          4,
          3,
          5
        ],
        "holes": [
          0,
          0,
          0,
          0,
          0,
          0,
          0,
          0,
          0,
          0,
          0,
          0,
          0,
          0,
          0,
          0,
          0,
          0
        ],
        "gross": 0,
        "net": 0
      },
      {
        "event_name": "Echo Falls",
        "date": "2025/08/02",
        "course": "Echo Falls",
        "par": [
          4,
          4,
          4,
          5,
          3,
          5,
          3,
          4,
          4,
          3,
          4,
          5,
          3,
          3,
          5,
          4,
          4,
          3
        ],
        "holes": [
          0,
          0,
          0,
          0,
          0,
          0,
          0,
          0,
          0,
          0,
          0,
          0,
          0,
          0,
          0,
          0,
          0,
          0
        ],
        "gross": 0,
        "net": 0
      },
      {
        "event_name": "Mt Si",
        "date": "2025/08/16",
        "course": "Mt Si",
        "par": [
          4,
          5,
          4,
          3,
          4,
          4,
          5,
          3,
          4,
          4,
          3,
          5,
          4,
          4,
          4,
          5,
          3,
          4
        ],
        "holes": [
          0,
          0,
          0,
          0,
          0,
          0,
          0,
          0,
          0,
          0,
          0,
          0,
          0,
          0,
          0,
          0,
          0,
          0
        ],
        "gross": 0,
        "net": 0
      },
      {
        "event_name": "Jackson",
        "date": "2025/09/06",
        "course": "Jackson",
        "par": [
          5,
          3,
          4,
          4,
          5,
          4,
          3,
          4,
          4,
          4,
          3,
          5,
          3,
          4,
          4,
          4,
          3,
          4
        ],
        "holes": [
          6,
          3,
          4,
          6,
          6,
          5,
          3,
          5,
          8,
          6,
          3,
          6,
          5,
          6,
          4,
          8,
          3,
          5
        ],
        "gross": 92,
        "net": 92
      }
    ],
    "season_averages": {
      "gross": null,
      "net": null,
      "finale_points": null,
      "purchase_points": null,
      "raffle_totals": null
    },
    "score_breakdown": {
      "eagle": 72,
      "birdie": 2,
      "par": 12,
      "bogey": 13,
      "double_or_worse": 9
    }
  },
  {
    "name": "Sejin",
    "slug": "sejin",
    "ghin": "",
    "events": [
      {
        "event_name": "West Seattle",
        "date": "2025/06/29",
        "course": "West Seattle",
        "par": [
          5,
          4,
          3,
          5,
          4,
          3,
          4,
          4,
          5,
          4,
          3,
          5,
          3,
          4,
          4,
          4,
          4,
          4
        ],
        "holes": [
          4,
          4,
          5,
          6,
          3,
          3,
          4,
          8,
          6,
          4,
          3,
          8,
          3,
          6,
          5,
          8,
          5,
          5
        ],
        "gross": 90,
        "net": 84.11097345132742
      },
      {
        "event_name": "Maplewood",
        "date": "2025/07/12",
        "course": "Maplewood",
        "par": [
          4,
          3,
          4,
          4,
          5,
          3,
          5,
          4,
          4,
          5,
          4,
          3,
          4,
          3,
          5,
          4,
          4,
          4
        ],
        "holes": [
          0,
          0,
          0,
          0,
          0,
          0,
          0,
          0,
          0,
          0,
          0,
          0,
          0,
          0,
          0,
          0,
          0,
          0
        ],
        "gross": 0,
        "net": 0
      },
      {
        "event_name": "Willows",
        "date": "2025/07/20",
        "course": "Willows - Eagle",
        "par": [
          4,
          5,
          4,
          4,
          4,
          4,
          3,
          4,
          3,
          5,
          5,
          4,
          4,
          3,
          4,
          4,
          3,
          5
        ],
        "holes": [
          0,
          0,
          0,
          0,
          0,
          0,
          0,
          0,
          0,
          0,
          0,
          0,
          0,
          0,
          0,
          0,
          0,
          0
        ],
        "gross": 0,
        "net": 0
      },
      {
        "event_name": "Echo Falls",
        "date": "2025/08/02",
        "course": "Echo Falls",
        "par": [
          4,
          4,
          4,
          5,
          3,
          5,
          3,
          4,
          4,
          3,
          4,
          5,
          3,
          3,
          5,
          4,
          4,
          3
        ],
        "holes": [
          0,
          0,
          0,
          0,
          0,
          0,
          0,
          0,
          0,
          0,
          0,
          0,
          0,
          0,
          0,
          0,
          0,
          0
        ],
        "gross": 0,
        "net": 0
      },
      {
        "event_name": "Mt Si",
        "date": "2025/08/16",
        "course": "Mt Si",
        "par": [
          4,
          5,
          4,
          3,
          4,
          4,
          5,
          3,
          4,
          4,
          3,
          5,
          4,
          4,
          4,
          5,
          3,
          4
        ],
        "holes": [
          0,
          0,
          0,
          0,
          0,
          0,
          0,
          0,
          0,
          0,
          0,
          0,
          0,
          0,
          0,
          0,
          0,
          0
        ],
        "gross": 0,
        "net": 0
      },
      {
        "event_name": "Jackson",
        "date": "2025/09/06",
        "course": "Jackson",
        "par": [
          5,
          3,
          4,
          4,
          5,
          4,
          3,
          4,
          4,
          4,
          3,
          5,
          3,
          4,
          4,
          4,
          3,
          4
        ],
        "holes": [
          7,
          3,
          5,
          5,
          5,
          6,
          6,
          5,
          4,
          8,
          4,
          5,
          3,
          7,
          6,
          6,
          6,
          5
        ],
        "gross": 96,
        "net": 96
      }
    ],
    "season_averages": {
      "gross": null,
      "net": null,
      "finale_points": null,
      "purchase_points": null,
      "raffle_totals": null
    },
    "score_breakdown": {
      "eagle": 72,
      "birdie": 2,
      "par": 11,
      "bogey": 10,
      "double_or_worse": 13
    }
  },
  {
    "name": "Kyle",
    "slug": "kyle",
    "ghin": "",
    "events": [
      {
        "event_name": "West Seattle",
        "date": "2025/06/29",
        "course": "West Seattle",
        "par": [
          5,
          4,
          3,
          5,
          4,
          3,
          4,
          4,
          5,
          4,
          3,
          5,
          3,
          4,
          4,
          4,
          4,
          4
        ],
        "holes": [
          6,
          4,
          5,
          6,
          6,
          4,
          4,
          5,
          7,
          5,
          4,
          6,
          4,
          4,
          5,
          4,
          4,
          6
        ],
        "gross": 89,
        "net": 79.19238938053097
      },
      {
        "event_name": "Maplewood",
        "date": "2025/07/12",
        "course": "Maplewood",
        "par": [
          4,
          3,
          4,
          4,
          5,
          3,
          5,
          4,
          4,
          5,
          4,
          3,
          4,
          3,
          5,
          4,
          4,
          4
        ],
        "holes": [
          0,
          0,
          0,
          0,
          0,
          0,
          0,
          0,
          0,
          0,
          0,
          0,
          0,
          0,
          0,
          0,
          0,
          0
        ],
        "gross": 0,
        "net": 0
      },
      {
        "event_name": "Willows",
        "date": "2025/07/20",
        "course": "Willows - Eagle",
        "par": [
          4,
          5,
          4,
          4,
          4,
          4,
          3,
          4,
          3,
          5,
          5,
          4,
          4,
          3,
          4,
          4,
          3,
          5
        ],
        "holes": [
          0,
          0,
          0,
          0,
          0,
          0,
          0,
          0,
          0,
          0,
          0,
          0,
          0,
          0,
          0,
          0,
          0,
          0
        ],
        "gross": 0,
        "net": 0
      },
      {
        "event_name": "Echo Falls",
        "date": "2025/08/02",
        "course": "Echo Falls",
        "par": [
          4,
          4,
          4,
          5,
          3,
          5,
          3,
          4,
          4,
          3,
          4,
          5,
          3,
          3,
          5,
          4,
          4,
          3
        ],
        "holes": [
          0,
          0,
          0,
          0,
          0,
          0,
          0,
          0,
          0,
          0,
          0,
          0,
          0,
          0,
          0,
          0,
          0,
          0
        ],
        "gross": 0,
        "net": 0
      },
      {
        "event_name": "Mt Si",
        "date": "2025/08/16",
        "course": "Mt Si",
        "par": [
          4,
          5,
          4,
          3,
          4,
          4,
          5,
          3,
          4,
          4,
          3,
          5,
          4,
          4,
          4,
          5,
          3,
          4
        ],
        "holes": [
          0,
          0,
          0,
          0,
          0,
          0,
          0,
          0,
          0,
          0,
          0,
          0,
          0,
          0,
          0,
          0,
          0,
          0
        ],
        "gross": 0,
        "net": 0
      },
      {
        "event_name": "Jackson",
        "date": "2025/09/06",
        "course": "Jackson",
        "par": [
          5,
          3,
          4,
          4,
          5,
          4,
          3,
          4,
          4,
          4,
          3,
          5,
          3,
          4,
          4,
          4,
          3,
          4
        ],
        "holes": [
          0,
          0,
          0,
          0,
          0,
          0,
          0,
          0,
          0,
          0,
          0,
          0,
          0,
          0,
          0,
          0,
          0,
          0
        ],
        "gross": 0,
        "net": 0
      }
    ],
    "season_averages": {
      "gross": null,
      "net": null,
      "finale_points": null,
      "purchase_points": null,
      "raffle_totals": null
    },
    "score_breakdown": {
      "eagle": 90,
      "birdie": 0,
      "par": 5,
      "bogey": 9,
      "double_or_worse": 4
    }
  },
  {
    "name": "",
    "slug": "",
    "ghin": "",
    "events": [
      {
        "event_name": "Home Course",
        "date": "2025/09/14",
        "course": "Home Course",
        "par": [
          4,
          4,
          4,
          3,
          5,
          3,
          4,
          5,
          4,
          5,
          4,
          3,
          4,
          3,
          4,
          5,
          4,
          4
        ],
        "holes": [
          0,
          0,
          0,
          0,
          0,
          0,
          0,
          0,
          0,
          0,
          0,
          0,
          0,
          0,
          0,
          0,
          0,
          0
        ],
        "gross": "",
        "net": ""
      }
    ],
    "season_averages": {},
    "score_breakdown": {
      "eagle": 18,
      "birdie": 0,
      "par": 0,
      "bogey": 0,
      "double_or_worse": 0
    }
  }
]